headjackai/__init__.py
headjackai/headjackai_hub.py
headjackai/preprocessing.py
headjackai/utils.py
headjackai_sdk-0.2.20.dist-info/METADATA
headjackai_sdk-0.2.20.dist-info/WHEEL
headjackai_sdk-0.2.20.dist-info/top_level.txt
headjackai_sdk-0.2.20.dist-info/RECORD
