Metadata-Version: 2.1
Name: headjackai-sdk
Version: 0.2.20
Summary: The SDK of Headjack-AI
Home-page: UNKNOWN
Author: chunting liu
Author-email: jim_liu@symphox.net
License: MIT Licence
Keywords: Headjack ai SDK
Platform: UNKNOWN
Classifier: Programming Language :: Python :: 3
Classifier: License :: OSI Approved :: MIT License
Classifier: Operating System :: OS Independent
Requires-Python: >=3.6
Requires-Dist: pandas (==1.1.5)
Requires-Dist: scikit-learn (==0.24.2)
Requires-Dist: requests (==2.26.0)
Requires-Dist: passlib (==1.7.4)
